// class version 61.0 (61)
// access flags 0x21
public class sourceCode/FinancialCal {

  // compiled from: FinancialCal.java
  // access flags 0x19
  public final static INNERCLASS java/lang/invoke/MethodHandles$Lookup java/lang/invoke/MethodHandles Lookup

  // access flags 0x1
  public <init>()V
   L0
    LINENUMBER 4 L0
    ALOAD 0
    INVOKESPECIAL java/lang/Object.<init> ()V
    RETURN
   L1
    LOCALVARIABLE this LsourceCode/FinancialCal; L0 L1 0
    MAXSTACK = 1
    MAXLOCALS = 1

  // access flags 0x9
  public static main([Ljava/lang/String;)V
   L0
    LINENUMBER 6 L0
    NEW java/util/Scanner
    DUP
    GETSTATIC java/lang/System.in : Ljava/io/InputStream;
    INVOKESPECIAL java/util/Scanner.<init> (Ljava/io/InputStream;)V
    ASTORE 1
   L1
    LINENUMBER 8 L1
    GETSTATIC java/lang/System.out : Ljava/io/PrintStream;
    LDC "Enter Debt Value"
    INVOKEVIRTUAL java/io/PrintStream.println (Ljava/lang/String;)V
   L2
    LINENUMBER 9 L2
    ALOAD 1
    INVOKEVIRTUAL java/util/Scanner.nextDouble ()D
    DSTORE 2
   L3
    LINENUMBER 10 L3
    GETSTATIC java/lang/System.out : Ljava/io/PrintStream;
    LDC "Enter Interest Rate"
    INVOKEVIRTUAL java/io/PrintStream.println (Ljava/lang/String;)V
   L4
    LINENUMBER 11 L4
    ALOAD 1
    INVOKEVIRTUAL java/util/Scanner.nextDouble ()D
    DSTORE 4
   L5
    LINENUMBER 12 L5
    GETSTATIC java/lang/System.out : Ljava/io/PrintStream;
    LDC "Enter Duration"
    INVOKEVIRTUAL java/io/PrintStream.println (Ljava/lang/String;)V
   L6
    LINENUMBER 13 L6
    ALOAD 1
    INVOKEVIRTUAL java/util/Scanner.nextInt ()I
    ISTORE 6
   L7
    LINENUMBER 16 L7
    DLOAD 2
    DLOAD 4
    ILOAD 6
    INVOKESTATIC sourceCode/FinancialCal.calculateMonthlyRate (DDI)D
    DSTORE 7
   L8
    LINENUMBER 19 L8
    DLOAD 2
    DLOAD 4
    ILOAD 6
    INVOKESTATIC sourceCode/FinancialCal.calculateOverallDebt (DDI)D
    DSTORE 9
   L9
    LINENUMBER 21 L9
    GETSTATIC java/lang/System.out : Ljava/io/PrintStream;
    DLOAD 7
    INVOKEDYNAMIC makeConcatWithConstants(D)Ljava/lang/String; [
      // handle kind 0x6 : INVOKESTATIC
      java/lang/invoke/StringConcatFactory.makeConcatWithConstants(Ljava/lang/invoke/MethodHandles$Lookup;Ljava/lang/String;Ljava/lang/invoke/MethodType;Ljava/lang/String;[Ljava/lang/Object;)Ljava/lang/invoke/CallSite;
      // arguments:
      "Monthly Rate: \u0001"
    ]
    INVOKEVIRTUAL java/io/PrintStream.println (Ljava/lang/String;)V
   L10
    LINENUMBER 22 L10
    GETSTATIC java/lang/System.out : Ljava/io/PrintStream;
    ILOAD 6
    INVOKEDYNAMIC makeConcatWithConstants(I)Ljava/lang/String; [
      // handle kind 0x6 : INVOKESTATIC
      java/lang/invoke/StringConcatFactory.makeConcatWithConstants(Ljava/lang/invoke/MethodHandles$Lookup;Ljava/lang/String;Ljava/lang/invoke/MethodType;Ljava/lang/String;[Ljava/lang/Object;)Ljava/lang/invoke/CallSite;
      // arguments:
      "Number of Rates: \u0001"
    ]
    INVOKEVIRTUAL java/io/PrintStream.println (Ljava/lang/String;)V
   L11
    LINENUMBER 23 L11
    GETSTATIC java/lang/System.out : Ljava/io/PrintStream;
    DLOAD 9
    INVOKEDYNAMIC makeConcatWithConstants(D)Ljava/lang/String; [
      // handle kind 0x6 : INVOKESTATIC
      java/lang/invoke/StringConcatFactory.makeConcatWithConstants(Ljava/lang/invoke/MethodHandles$Lookup;Ljava/lang/String;Ljava/lang/invoke/MethodType;Ljava/lang/String;[Ljava/lang/Object;)Ljava/lang/invoke/CallSite;
      // arguments:
      "Overall Debt: \u0001"
    ]
    INVOKEVIRTUAL java/io/PrintStream.println (Ljava/lang/String;)V
   L12
    LINENUMBER 24 L12
    RETURN
   L13
    LOCALVARIABLE args [Ljava/lang/String; L0 L13 0
    LOCALVARIABLE scanner Ljava/util/Scanner; L1 L13 1
    LOCALVARIABLE debtValue D L3 L13 2
    LOCALVARIABLE interestRate D L5 L13 4
    LOCALVARIABLE paybackDuration I L7 L13 6
    LOCALVARIABLE monthlyRate D L8 L13 7
    LOCALVARIABLE overallDebt D L9 L13 9
    MAXSTACK = 5
    MAXLOCALS = 11

  // access flags 0x9
  public static calculateMonthlyRate(DDI)D
   L0
    LINENUMBER 27 L0
    DCONST_0
    DSTORE 5
   L1
    LINENUMBER 28 L1
    DLOAD 0
    DCONST_0
    DCMPL
    IFLE L2
    DLOAD 2
    DCONST_0
    DCMPL
    IFLE L2
    ILOAD 4
    IFLE L2
   L3
    LINENUMBER 29 L3
    DLOAD 0
    ILOAD 4
    I2D
    DDIV
    DLOAD 0
    DLOAD 2
    ILOAD 4
    I2D
    DDIV
    DMUL
    LDC 0.01
    DMUL
    DADD
    DSTORE 5
   L2
    LINENUMBER 31 L2
   FRAME FULL [D D I D] []
    DLOAD 5
    DRETURN
   L4
    LOCALVARIABLE debtValue D L0 L4 0
    LOCALVARIABLE interestRate D L0 L4 2
    LOCALVARIABLE paybackDuration I L0 L4 4
    LOCALVARIABLE monthly_rate D L1 L4 5
    MAXSTACK = 8
    MAXLOCALS = 7

  // access flags 0x9
  public static calculateOverallDebt(DDI)D
   L0
    LINENUMBER 35 L0
    DLOAD 0
    DLOAD 2
    ILOAD 4
    INVOKESTATIC sourceCode/FinancialCal.calculateMonthlyRate (DDI)D
    ILOAD 4
    I2D
    DMUL
    INVOKESTATIC java/lang/Math.abs (D)D
    POP2
    DCONST_0
    DRETURN
   L1
    LOCALVARIABLE debtValue D L0 L1 0
    LOCALVARIABLE interestRate D L0 L1 2
    LOCALVARIABLE paybackDuration I L0 L1 4
    MAXSTACK = 5
    MAXLOCALS = 5
}

