// class version 61.0 (61)
// access flags 0x21
public class sourceCode/FinancialCalTest {

  // compiled from: FinancialCalTest.java

  // access flags 0x1
  public <init>()V
   L0
    LINENUMBER 7 L0
    ALOAD 0
    INVOKESPECIAL java/lang/Object.<init> ()V
    RETURN
   L1
    LOCALVARIABLE this LsourceCode/FinancialCalTest; L0 L1 0
    MAXSTACK = 1
    MAXLOCALS = 1

  // access flags 0x1
  public testMonthlyRate()V
  @Lorg/junit/Test;()
   L0
    LINENUMBER 11 L0
    NEW sourceCode/FinancialCal
    DUP
    INVOKESPECIAL sourceCode/FinancialCal.<init> ()V
    ASTORE 1
   L1
    LINENUMBER 12 L1
    DCONST_0
    ALOAD 1
    POP
    DCONST_0
    DCONST_0
    ICONST_0
    INVOKESTATIC sourceCode/FinancialCal.calculateMonthlyRate (DDI)D
    INVOKESTATIC org/junit/jupiter/api/Assertions.assertEquals (DD)V
   L2
    LINENUMBER 13 L2
    DCONST_0
    ALOAD 1
    POP
    LDC -2000.0
    LDC -5.0
    BIPUSH -24
    INVOKESTATIC sourceCode/FinancialCal.calculateMonthlyRate (DDI)D
    INVOKESTATIC org/junit/jupiter/api/Assertions.assertEquals (DD)V
   L3
    LINENUMBER 14 L3
    LDC 87.5
    ALOAD 1
    POP
    LDC 1000.0
    LDC 5.0
    BIPUSH 12
    INVOKESTATIC sourceCode/FinancialCal.calculateMonthlyRate (DDI)D
    INVOKESTATIC org/junit/jupiter/api/Assertions.assertEquals (DD)V
   L4
    LINENUMBER 15 L4
    RETURN
   L5
    LOCALVARIABLE this LsourceCode/FinancialCalTest; L0 L5 0
    LOCALVARIABLE fc LsourceCode/FinancialCal; L1 L5 1
    MAXSTACK = 7
    MAXLOCALS = 2

  // access flags 0x1
  public testOverallDebt()V
  @Lorg/junit/Test;()
   L0
    LINENUMBER 19 L0
    NEW sourceCode/FinancialCal
    DUP
    INVOKESPECIAL sourceCode/FinancialCal.<init> ()V
    ASTORE 1
   L1
    LINENUMBER 20 L1
    DCONST_0
    ALOAD 1
    POP
    DCONST_0
    DCONST_0
    ICONST_0
    INVOKESTATIC sourceCode/FinancialCal.calculateOverallDebt (DDI)D
    INVOKESTATIC org/junit/jupiter/api/Assertions.assertEquals (DD)V
   L2
    LINENUMBER 21 L2
    DCONST_0
    ALOAD 1
    POP
    LDC -2000.0
    LDC -5.0
    BIPUSH -24
    INVOKESTATIC sourceCode/FinancialCal.calculateOverallDebt (DDI)D
    INVOKESTATIC org/junit/jupiter/api/Assertions.assertEquals (DD)V
   L3
    LINENUMBER 22 L3
    LDC 1050.0
    ALOAD 1
    POP
    LDC 1000.0
    LDC 5.0
    BIPUSH 12
    INVOKESTATIC sourceCode/FinancialCal.calculateOverallDebt (DDI)D
    INVOKESTATIC org/junit/jupiter/api/Assertions.assertEquals (DD)V
   L4
    LINENUMBER 23 L4
    RETURN
   L5
    LOCALVARIABLE this LsourceCode/FinancialCalTest; L0 L5 0
    LOCALVARIABLE fc LsourceCode/FinancialCal; L1 L5 1
    MAXSTACK = 7
    MAXLOCALS = 2
}

