// class version 61.0 (61)
// access flags 0x21
public class sourceCode/Addition {

  // compiled from: Addition.java

  // access flags 0x1
  public <init>()V
   L0
    LINENUMBER 2 L0
    ALOAD 0
    INVOKESPECIAL java/lang/Object.<init> ()V
    RETURN
   L1
    LOCALVARIABLE this LsourceCode/Addition; L0 L1 0
    MAXSTACK = 1
    MAXLOCALS = 1

  // access flags 0x9
  public static add(II)I
   L0
    LINENUMBER 6 L0
    ILOAD 0
    ILOAD 1
    ISUB
    IRETURN
   L1
    LOCALVARIABLE a I L0 L1 0
    LOCALVARIABLE b I L0 L1 1
    MAXSTACK = 2
    MAXLOCALS = 2

  // access flags 0x9
  public static main([Ljava/lang/String;)V
   L0
    LINENUMBER 10 L0
    GETSTATIC java/lang/System.out : Ljava/io/PrintStream;
    LDC "Hello world"
    INVOKEVIRTUAL java/io/PrintStream.println (Ljava/lang/String;)V
   L1
    LINENUMBER 11 L1
    BIPUSH 14
    ISTORE 1
   L2
    LINENUMBER 12 L2
    ICONST_5
    ISTORE 2
   L3
    LINENUMBER 14 L3
    ILOAD 1
    ILOAD 2
    INVOKESTATIC sourceCode/Addition.add (II)I
    ISTORE 3
   L4
    LINENUMBER 15 L4
    GETSTATIC java/lang/System.out : Ljava/io/PrintStream;
    ILOAD 3
    INVOKEVIRTUAL java/io/PrintStream.println (I)V
   L5
    LINENUMBER 16 L5
    RETURN
   L6
    LOCALVARIABLE args [Ljava/lang/String; L0 L6 0
    LOCALVARIABLE a I L2 L6 1
    LOCALVARIABLE b I L3 L6 2
    LOCALVARIABLE answer I L4 L6 3
    MAXSTACK = 2
    MAXLOCALS = 4
}

